{
    "ID": "ff491423-614c-4893-88b3-1f1afa94ea8e",
    "Version": "2.3.4",
    "Name": "tgowrunani5",
    "Content": {
        "Content": {
            "Animation": {
                "Duration": 24,
                "Speed": 0.4,
                "Timelines": [
                    {
                        "ActionTag": 1157986017,
                        "Property": "FileData",
                        "Frames": [
                            {
                                "TextureFile": {
                                    "Type": "PlistSubImage",
                                    "Path": "tgowrunani5_01.png",
                                    "Plist": "tgowanipng.plist"
                                },
                                "FrameIndex": 0,
                                "Tween": false,
                                "ctype": "TextureFrameData"
                            },
                            {
                                "TextureFile": {
                                    "Type": "PlistSubImage",
                                    "Path": "tgowrunani5_02.png",
                                    "Plist": "tgowanipng.plist"
                                },
                                "FrameIndex": 2,
                                "Tween": false,
                                "ctype": "TextureFrameData"
                            },
                            {
                                "TextureFile": {
                                    "Type": "PlistSubImage",
                                    "Path": "tgowrunani5_03.png",
                                    "Plist": "tgowanipng.plist"
                                },
                                "FrameIndex": 4,
                                "Tween": false,
                                "ctype": "TextureFrameData"
                            },
                            {
                                "TextureFile": {
                                    "Type": "PlistSubImage",
                                    "Path": "tgowrunani5_04.png",
                                    "Plist": "tgowanipng.plist"
                                },
                                "FrameIndex": 6,
                                "Tween": false,
                                "ctype": "TextureFrameData"
                            },
                            {
                                "TextureFile": {
                                    "Type": "PlistSubImage",
                                    "Path": "tgowrunani5_05.png",
                                    "Plist": "tgowanipng.plist"
                                },
                                "FrameIndex": 8,
                                "Tween": false,
                                "ctype": "TextureFrameData"
                            },
                            {
                                "TextureFile": {
                                    "Type": "PlistSubImage",
                                    "Path": "tgowrunani5_06.png",
                                    "Plist": "tgowanipng.plist"
                                },
                                "FrameIndex": 10,
                                "Tween": false,
                                "ctype": "TextureFrameData"
                            },
                            {
                                "TextureFile": {
                                    "Type": "PlistSubImage",
                                    "Path": "tgowrunani5_07.png",
                                    "Plist": "tgowanipng.plist"
                                },
                                "FrameIndex": 12,
                                "Tween": false,
                                "ctype": "TextureFrameData"
                            },
                            {
                                "TextureFile": {
                                    "Type": "PlistSubImage",
                                    "Path": "tgowrunani5_08.png",
                                    "Plist": "tgowanipng.plist"
                                },
                                "FrameIndex": 14,
                                "Tween": false,
                                "ctype": "TextureFrameData"
                            },
                            {
                                "TextureFile": {
                                    "Type": "PlistSubImage",
                                    "Path": "tgowrunani5_09.png",
                                    "Plist": "tgowanipng.plist"
                                },
                                "FrameIndex": 16,
                                "Tween": false,
                                "ctype": "TextureFrameData"
                            },
                            {
                                "TextureFile": {
                                    "Type": "PlistSubImage",
                                    "Path": "tgowrunani5_10.png",
                                    "Plist": "tgowanipng.plist"
                                },
                                "FrameIndex": 18,
                                "Tween": false,
                                "ctype": "TextureFrameData"
                            },
                            {
                                "TextureFile": {
                                    "Type": "PlistSubImage",
                                    "Path": "tgowrunani5_11.png",
                                    "Plist": "tgowanipng.plist"
                                },
                                "FrameIndex": 20,
                                "Tween": false,
                                "ctype": "TextureFrameData"
                            },
                            {
                                "TextureFile": {
                                    "Type": "PlistSubImage",
                                    "Path": "tgowrunani5_12.png",
                                    "Plist": "tgowanipng.plist"
                                },
                                "FrameIndex": 22,
                                "Tween": false,
                                "ctype": "TextureFrameData"
                            },
                            {
                                "TextureFile": {
                                    "Type": "PlistSubImage",
                                    "Path": "tgowrunani5_01.png",
                                    "Plist": "tgowanipng.plist"
                                },
                                "FrameIndex": 24,
                                "Tween": false,
                                "ctype": "TextureFrameData"
                            }
                        ],
                        "ctype": "TimelineData"
                    }
                ],
                "ctype": "TimelineActionData"
            },
            "AnimationList": [],
            "ObjectData": {
                "Tag": 249,
                "Children": [
                    {
                        "FileData": {
                            "Type": "PlistSubImage",
                            "Path": "tgowrunani5_06.png",
                            "Plist": "tgowanipng.plist"
                        },
                        "BlendFunc": {
                            "Src": 1,
                            "Dst": 771
                        },
                        "AnchorPoint": {
                            "ScaleX": 0.5,
                            "ScaleY": 0.5
                        },
                        "Position": {
                            "X": 0,
                            "Y": 0
                        },
                        "Scale": {
                            "ScaleX": 1,
                            "ScaleY": 1
                        },
                        "CColor": {},
                        "IconVisible": false,
                        "PrePosition": {
                            "X": 0,
                            "Y": 0
                        },
                        "PreSize": {
                            "X": 0,
                            "Y": 0
                        },
                        "LeftMargin": -23,
                        "RightMargin": -23,
                        "TopMargin": -23,
                        "BottomMargin": -23,
                        "Tag": 271,
                        "ActionTag": 1157986017,
                        "Size": {
                            "X": 189,
                            "Y": 183
                        },
                        "Name": "Sprite_1",
                        "ctype": "SpriteObjectData"
                    }
                ],
                "Size": {
                    "X": 0,
                    "Y": 0
                },
                "Name": "Node",
                "ctype": "SingleNodeObjectData"
            },
            "UsedResources": [
                "tgowanipng.plist",
                "tgowanipng.png"
            ],
            "ctype": "GameFileData"
        }
    },
    "Type": "Node"
}